juv/__init__.py
juv/_add.py
juv/_cat.py
juv/_clear.py
juv/_edit.py
juv/_exec.py
juv/_export.py
juv/_init.py
juv/_lock.py
juv/_nbutils.py
juv/_pep723.py
juv/_remove.py
juv/_run.py
juv/_run_managed.py
juv/_run_replace.py
juv/_run_template.py
juv/_stamp.py
juv/_tree.py
juv/_utils.py
juv/_uv.py
juv/_venv.py
juv/_version.py
juv/py.typed
juv/static/setup.py
juv-0.4.4.dist-info/METADATA
juv-0.4.4.dist-info/WHEEL
juv-0.4.4.dist-info/entry_points.txt
juv-0.4.4.dist-info/licenses/LICENSE
juv-0.4.4.dist-info/RECORD
