Metadata-Version: 2.4
Name: juv
Version: 0.4.4
Summary: A toolkit for reproducible Jupyter notebooks, powered by uv.
Author-email: Trevor Manz <trevor.j.manz@gmail.com>
License: MIT
License-File: LICENSE
Classifier: Environment :: Console
Classifier: Intended Audience :: Developers
Classifier: License :: OSI Approved :: MIT License
Classifier: Operating System :: OS Independent
Classifier: Programming Language :: Python
Classifier: Programming Language :: Python :: 3 :: Only
Classifier: Programming Language :: Python :: 3.8
Classifier: Programming Language :: Python :: 3.9
Classifier: Programming Language :: Python :: 3.10
Classifier: Programming Language :: Python :: 3.11
Classifier: Programming Language :: Python :: 3.12
Classifier: Programming Language :: Python :: 3.13
Requires-Python: >=3.8
Requires-Dist: click>=8.1.7
Requires-Dist: jupytext>=1.16.4
Requires-Dist: rich>=13.9.2
Requires-Dist: tomlkit>=0.13.2
Requires-Dist: uv<0.8.0,>=0.7.0
Requires-Dist: whenever>=0.9.1; python_version >= '3.9'
